{
  "product_name": "400ml 브로우용기",
  "images": [
    {
      "source": "img_tag",
      "url": "http://chungjinkorea.com/data/goodsImages/GOODS1_1660636072.jpg",
      "filename": "GOODS1_1660636072.jpg",
      "alt": "400ml 브로우용기",
      "type": "main",
      "width": 1000,
      "height": 1000
    },
    {
      "source": "css_background",
      "url": "http://chungjinkorea.com/data/goodsImages/ADD_GOODS1_1660636072.jpg",
      "filename": "ADD_GOODS1_1660636072.jpg",
      "type": "main"
    },
    {
      "source": "css_background",
      "url": "http://chungjinkorea.com/data/goodsImages/1660636072_1.jpg",
      "filename": "1660636072_1.jpg",
      "type": "unknown"
    }
  ],
  "specifications": {
    "Phone": "032-674- 2748~9",
    "Fax": "032-681-2748",
    "Email": "chungjin@chungjinkorea.com"
  },
  "print_area_url": "http://chungjinkorea.com/bbs/goods_download.php?download=1&idx=616",
  "downloaded_images": [
    {
      "source": "img_tag",
      "url": "http://chungjinkorea.com/data/goodsImages/GOODS1_1660636072.jpg",
      "filename": "GOODS1_1660636072.jpg",
      "alt": "400ml 브로우용기",
      "type": "main",
      "width": 1000,
      "height": 1000,
      "local_path": "data/crawled_products/images/idx_616_main_1.jpg"
    },
    {
      "source": "css_background",
      "url": "http://chungjinkorea.com/data/goodsImages/ADD_GOODS1_1660636072.jpg",
      "filename": "ADD_GOODS1_1660636072.jpg",
      "type": "main",
      "local_path": "data/crawled_products/images/idx_616_main_2.jpg"
    },
    {
      "source": "css_background",
      "url": "http://chungjinkorea.com/data/goodsImages/1660636072_1.jpg",
      "filename": "1660636072_1.jpg",
      "type": "unknown",
      "local_path": "data/crawled_products/images/idx_616_unknown_3.jpg"
    }
  ],
  "print_area_local_path": "data/crawled_products/print_area/idx_616_print_area.pdf",
  "idx": "616",
  "url": "http://chungjinkorea.com/kr/product/view.php?idx=616",
  "crawled_at": "2025-10-18T12:44:11.268178"
}