{
  "product_name": "150ml 브로우용기",
  "images": [
    {
      "source": "img_tag",
      "url": "http://chungjinkorea.com/data/goodsImages/GOODS1_1658116470.jpg",
      "filename": "GOODS1_1658116470.jpg",
      "alt": "150ml 브로우용기",
      "type": "main",
      "width": 1000,
      "height": 1000
    }
  ],
  "specifications": {
    "제품명": "150ml 브로우용기",
    "제품 코드": "BE150-R002",
    "재질(원료)": "PE",
    "사양": "44x133(mm)/Ø24"
  },
  "print_area_url": null,
  "downloaded_images": [
    {
      "source": "img_tag",
      "url": "http://chungjinkorea.com/data/goodsImages/GOODS1_1658116470.jpg",
      "filename": "GOODS1_1658116470.jpg",
      "alt": "150ml 브로우용기",
      "type": "main",
      "width": 1000,
      "height": 1000,
      "local_path": "/Users/oypnus/Project/rag-enterprise/data/crawled_products_updated/images/idx_33_main_1.jpg"
    }
  ],
  "idx": "33",
  "url": "http://chungjinkorea.com/kr/product/view.php?idx=33",
  "crawled_at": "2025-10-18T21:18:19.382150"
}