{
  "product_name": "200ml 알약용기",
  "images": [
    {
      "source": "css_background",
      "url": "http://chungjinkorea.com/data/goodsImages/ADD_GOODS2_171098835120250827140805.jpg",
      "filename": "ADD_GOODS2_171098835120250827140805.jpg",
      "type": "additional_2",
      "local_path": "data/crawled_products_final/Bottle/PE/images/idx_882_additional_2_1.jpg"
    },
    {
      "source": "img_tag",
      "url": "http://chungjinkorea.com/data/goodsImages/GOODS1_171098835120250827140805.jpg",
      "filename": "GOODS1_171098835120250827140805.jpg",
      "alt": "200ml 알약용기",
      "type": "main",
      "width": 1000,
      "height": 1000,
      "local_path": "data/crawled_products_final/Bottle/PE/images/idx_882_main_2.jpg"
    },
    {
      "source": "css_background",
      "url": "http://chungjinkorea.com/data/goodsImages/ADD_GOODS1_171098835120250827140805.jpg",
      "filename": "ADD_GOODS1_171098835120250827140805.jpg",
      "type": "main",
      "local_path": "data/crawled_products_final/Bottle/PE/images/idx_882_main_3.jpg"
    }
  ],
  "specifications": {
    "제품명": "200ml 알약용기",
    "제품 코드": "BE200-P001",
    "재질(원료)": "PE",
    "사양": "60x109(mm)",
    "capacity": "200ml",
    "dimensions": "Ø38",
    "neck_size": "38파이",
    "neck_size_mm": 38,
    "neck_updated_at": "2025-10-23T21:00:50.674681",
    "moq": "10,000개"
  },
  "print_area_url": "http://chungjinkorea.com/bbs/goods_download.php?download=1&idx=882",
  "downloaded_images": [
    {
      "source": "css_background",
      "url": "http://chungjinkorea.com/data/goodsImages/ADD_GOODS2_171098835120250827140805.jpg",
      "filename": "ADD_GOODS2_171098835120250827140805.jpg",
      "type": "additional_2",
      "local_path": "data/crawled_products_final/Bottle/PE/images/idx_882_additional_2_1.jpg"
    },
    {
      "source": "img_tag",
      "url": "http://chungjinkorea.com/data/goodsImages/GOODS1_171098835120250827140805.jpg",
      "filename": "GOODS1_171098835120250827140805.jpg",
      "alt": "200ml 알약용기",
      "type": "main",
      "width": 1000,
      "height": 1000,
      "local_path": "data/crawled_products_final/Bottle/PE/images/idx_882_main_2.jpg"
    },
    {
      "source": "css_background",
      "url": "http://chungjinkorea.com/data/goodsImages/ADD_GOODS1_171098835120250827140805.jpg",
      "filename": "ADD_GOODS1_171098835120250827140805.jpg",
      "type": "main",
      "local_path": "data/crawled_products_final/Bottle/PE/images/idx_882_main_3.jpg"
    }
  ],
  "print_area_local_path": "data/crawled_products_final/PE/print_area/idx_882_print_area.pdf",
  "idx": "882",
  "url": "http://chungjinkorea.com/kr/product/view.php?idx=882",
  "crawled_at": "2025-10-18T21:15:26.746986",
  "category_label": "bottle",
  "pricing": {
    "actual_capacity_ml": 200,
    "matched_price_range": "200",
    "material": "PE",
    "thickness": null,
    "base_price": {
      "regular": 260,
      "discount": 190
    },
    "printing_option": null,
    "label_option": null,
    "material_metadata": null,
    "regular_price": 260,
    "discount_price": 190,
    "capacity_ml": 200,
    "material_detail": "PE/PET",
    "pricing_updated_at": "2025-10-23T20:42:24.148291",
    "pricing_capacity_ml": 200
  },
  "pricing_added_at": "2025-10-23",
  "pricing_updated_at": "2025-10-23T18:25:51.922023",
  "compatibility_analysis": {
    "analyzed_at": "2025-10-24T01:29:09.779161",
    "analysis_version": "1.0.0",
    "product_info": {
      "idx": "882",
      "product_name": "200ml 알약용기",
      "product_code": "BE200-P001",
      "category_type": "BOTTLE",
      "neck_size": "38파이",
      "capacity_ml": 200.0,
      "material": "PE"
    },
    "compatible_caps_pumps": {
      "count": 0,
      "items": []
    },
    "recommended_applications": {
      "by_capacity": [
        "토너",
        "스킨",
        "샴푸",
        "바디워시"
      ],
      "by_material": [
        "수분 기반 토너",
        "로션/에멀젼",
        "에센스 (저점도)",
        "민감성 제품",
        "베이비 케어"
      ],
      "combined_recommendation": [
        "수분 기반 토너"
      ],
      "recommended_neck_sizes": [
        "24파이",
        "28파이"
      ],
      "unsuitable_products": [
        "고농도 오일 (>30%)",
        "고농도 알코올 (>30%)",
        "강산성 제품 (pH <3)",
        "강염기성 제품 (pH >11)"
      ],
      "material_warnings": [],
      "chemical_resistance": {
        "water_based": "excellent",
        "low_oil": "good",
        "high_oil": "poor",
        "alcohol_low": "good",
        "alcohol_high": "avoid",
        "ph_range": "4-10"
      }
    },
    "material_info": {
      "name": "Polyethylene (폴리에틸렌)",
      "characteristics": "내화학성 우수, 유연성, 경제적",
      "suitable_products": [
        "수분 기반 토너",
        "로션/에멀젼",
        "에센스 (저점도)",
        "민감성 제품",
        "베이비 케어"
      ],
      "unsuitable_products": [
        "고농도 오일 (>30%)",
        "고농도 알코올 (>30%)",
        "강산성 제품 (pH <3)",
        "강염기성 제품 (pH >11)"
      ],
      "chemical_resistance": {
        "water_based": "excellent",
        "low_oil": "good",
        "high_oil": "poor",
        "alcohol_low": "good",
        "alcohol_high": "avoid",
        "ph_range": "4-10"
      }
    }
  }
}