{
  "product_name": "320ml 튜브브로우용기",
  "images": [
    {
      "source": "img_tag",
      "url": "http://chungjinkorea.com/data/goodsImages/GOODS1_1660006815.jpg",
      "filename": "GOODS1_1660006815.jpg",
      "alt": "320ml 튜브브로우용기",
      "type": "main",
      "width": 1000,
      "height": 1000
    }
  ],
  "specifications": {
    "제품명": "320ml 튜브브로우용기",
    "제품 코드": "TE320-H002",
    "재질(원료)": "PE",
    "사양": "78x41x185(mm)",
    "capacity": "320ml",
    "dimensions": "Ø18",
    "neck_size": "18파이",
    "neck_size_mm": 18,
    "neck_updated_at": "2025-10-23T21:00:50.591479",
    "moq": "10,000개"
  },
  "print_area_url": "http://chungjinkorea.com/bbs/goods_download.php?download=1&idx=481",
  "downloaded_images": [
    {
      "source": "img_tag",
      "url": "http://chungjinkorea.com/data/goodsImages/GOODS1_1660006815.jpg",
      "filename": "GOODS1_1660006815.jpg",
      "alt": "320ml 튜브브로우용기",
      "type": "main",
      "width": 1000,
      "height": 1000,
      "local_path": "data/crawled_products_final/Bottle/PE/images/idx_481_main_1.jpg"
    }
  ],
  "print_area_local_path": "data/crawled_products_final/temp_complete_crawl/print_area/idx_481_print_area.pdf",
  "idx": "481",
  "url": "http://chungjinkorea.com/kr/product/view.php?idx=481",
  "crawled_at": "2025-10-21T22:03:22.175990",
  "category_label": "bottle",
  "pricing": {
    "actual_capacity_ml": 320,
    "matched_price_range": "400",
    "material": "PE",
    "thickness": null,
    "base_price": {
      "regular": 330,
      "discount": 250
    },
    "printing_option": null,
    "label_option": null,
    "material_metadata": null,
    "regular_price": 300,
    "discount_price": 230,
    "pricing_capacity_ml": 300,
    "material_detail": "PE/PET",
    "pricing_updated_at": "2025-10-23T20:42:24.108738"
  },
  "pricing_updated_at": "2025-10-23T18:25:51.814210"
}