{
  "product_name": "1100ml 브로우용기",
  "images": [
    {
      "source": "css_background",
      "url": "http://chungjinkorea.com/data/goodsImages/ADD_GOODS2_173433631320250321130329.jpg",
      "filename": "ADD_GOODS2_173433631320250321130329.jpg",
      "type": "additional_2",
      "local_path": "data/crawled_products_final/Bottle/PE/images/idx_914_additional_2_1.jpg"
    },
    {
      "source": "css_background",
      "url": "http://chungjinkorea.com/data/goodsImages/ADD_GOODS3_173433631320250321130329.jpg",
      "filename": "ADD_GOODS3_173433631320250321130329.jpg",
      "type": "additional_3",
      "local_path": "data/crawled_products_final/Bottle/PE/images/idx_914_additional_3_2.jpg"
    },
    {
      "source": "img_tag",
      "url": "http://chungjinkorea.com/data/goodsImages/GOODS1_173433631320250321130329.jpg",
      "filename": "GOODS1_173433631320250321130329.jpg",
      "alt": "1100ml 브로우용기",
      "type": "main",
      "width": 1000,
      "height": 1000,
      "local_path": "data/crawled_products_final/Bottle/PE/images/idx_914_main_3.jpg"
    },
    {
      "source": "css_background",
      "url": "http://chungjinkorea.com/data/goodsImages/ADD_GOODS1_173433631320250321130329.jpg",
      "filename": "ADD_GOODS1_173433631320250321130329.jpg",
      "type": "main",
      "local_path": "data/crawled_products_final/Bottle/PE/images/idx_914_main_4.jpg"
    }
  ],
  "specifications": {
    "제품명": "1100ml 브로우용기",
    "제품 코드": "BE111-R005",
    "재질(원료)": "PE",
    "사양": "93x208(mm)",
    "capacity": "1100ml",
    "dimensions": "Ø32",
    "neck_size": "32파이",
    "neck_size_mm": 32,
    "neck_updated_at": "2025-10-23T21:00:50.652657",
    "moq": "10,000개"
  },
  "print_area_url": "http://chungjinkorea.com/bbs/goods_download.php?download=1&idx=914",
  "downloaded_images": [
    {
      "source": "css_background",
      "url": "http://chungjinkorea.com/data/goodsImages/ADD_GOODS2_173433631320250321130329.jpg",
      "filename": "ADD_GOODS2_173433631320250321130329.jpg",
      "type": "additional_2",
      "local_path": "data/crawled_products_final/Bottle/PE/images/idx_914_additional_2_1.jpg"
    },
    {
      "source": "css_background",
      "url": "http://chungjinkorea.com/data/goodsImages/ADD_GOODS3_173433631320250321130329.jpg",
      "filename": "ADD_GOODS3_173433631320250321130329.jpg",
      "type": "additional_3",
      "local_path": "data/crawled_products_final/Bottle/PE/images/idx_914_additional_3_2.jpg"
    },
    {
      "source": "img_tag",
      "url": "http://chungjinkorea.com/data/goodsImages/GOODS1_173433631320250321130329.jpg",
      "filename": "GOODS1_173433631320250321130329.jpg",
      "alt": "1100ml 브로우용기",
      "type": "main",
      "width": 1000,
      "height": 1000,
      "local_path": "data/crawled_products_final/Bottle/PE/images/idx_914_main_3.jpg"
    },
    {
      "source": "css_background",
      "url": "http://chungjinkorea.com/data/goodsImages/ADD_GOODS1_173433631320250321130329.jpg",
      "filename": "ADD_GOODS1_173433631320250321130329.jpg",
      "type": "main",
      "local_path": "data/crawled_products_final/Bottle/PE/images/idx_914_main_4.jpg"
    }
  ],
  "print_area_local_path": "data/crawled_products_final/PE/print_area/idx_914_print_area.pdf",
  "idx": "914",
  "url": "http://chungjinkorea.com/kr/product/view.php?idx=914",
  "crawled_at": "2025-10-18T21:33:23.689477",
  "category_label": "bottle",
  "pricing": {
    "actual_capacity_ml": 1100,
    "matched_price_range": "100",
    "material": "PE",
    "thickness": null,
    "base_price": {
      "regular": 180,
      "discount": 130
    },
    "printing_option": null,
    "label_option": null,
    "material_metadata": null,
    "regular_price": 460,
    "discount_price": 420,
    "pricing_capacity_ml": 1000,
    "material_detail": "PE/PET",
    "pricing_updated_at": "2025-10-23T20:42:24.140358"
  },
  "pricing_added_at": "2025-10-23",
  "pricing_updated_at": "2025-10-23T18:25:51.909278",
  "compatibility_analysis": {
    "analyzed_at": "2025-10-24T01:29:09.765215",
    "analysis_version": "1.0.0",
    "product_info": {
      "idx": "914",
      "product_name": "1100ml 브로우용기",
      "product_code": "BE111-R005",
      "category_type": "BOTTLE",
      "neck_size": "32파이",
      "capacity_ml": 1100.0,
      "material": "PE"
    },
    "compatible_caps_pumps": {
      "count": 18,
      "items": [
        {
          "idx": "692",
          "product_name": "32파이 고점도펌프",
          "product_code": "PO032-CG12",
          "neck_size": "32파이",
          "category_type": "PUMP",
          "material": "기타",
          "spec": "32파이 고점도펌프",
          "vendor": "지에프",
          "pricing": {
            "supply_price": null,
            "selling_price": null
          }
        },
        {
          "idx": "689",
          "product_name": "32파이 고점도펌프",
          "product_code": "PO032-CG07",
          "neck_size": "32파이",
          "category_type": "PUMP",
          "material": "기타",
          "spec": "32파이 고점도펌프",
          "vendor": "지에프테크",
          "pricing": {
            "supply_price": null,
            "selling_price": null
          }
        },
        {
          "idx": "694",
          "product_name": "32파이 리무버 펌프",
          "product_code": "PO032-CG14",
          "neck_size": "32파이",
          "category_type": "PUMP",
          "material": "기타",
          "spec": "32파이 리무버 펌프",
          "vendor": "지에프",
          "pricing": {
            "supply_price": null,
            "selling_price": null
          }
        },
        {
          "idx": "693",
          "product_name": "32파이 무광 고점도펌프",
          "product_code": "PO032-CG13(M)",
          "neck_size": "32파이",
          "category_type": "PUMP",
          "material": "기타",
          "spec": "32파이 무광 고점도펌프",
          "vendor": "지에프",
          "pricing": {
            "supply_price": null,
            "selling_price": null
          }
        },
        {
          "idx": "847",
          "product_name": "32파이 무광 고점도펌프",
          "product_code": "PO032-CG16(M)",
          "neck_size": "32파이",
          "category_type": "PUMP",
          "material": "기타",
          "spec": "32파이 무광 고점도펌프",
          "vendor": "지에프",
          "pricing": {
            "supply_price": null,
            "selling_price": null
          }
        },
        {
          "idx": "681",
          "product_name": "32파이 일반펌프",
          "product_code": "PO032-CG04",
          "neck_size": "32파이",
          "category_type": "PUMP",
          "material": "기타",
          "spec": "32파이 일반펌프",
          "vendor": "지에프테크",
          "pricing": {
            "supply_price": null,
            "selling_price": null
          }
        },
        {
          "idx": "669",
          "product_name": "32파이 일반펌프",
          "product_code": "PO032-CG02",
          "neck_size": "32파이",
          "category_type": "PUMP",
          "material": "기타",
          "spec": "32파이 일반펌프",
          "vendor": "지에프테크",
          "pricing": {
            "supply_price": null,
            "selling_price": null
          }
        },
        {
          "idx": "675",
          "product_name": "32파이 일반펌프",
          "product_code": "PO032-CG03",
          "neck_size": "32파이",
          "category_type": "PUMP",
          "material": "기타",
          "spec": "32파이 일반펌프",
          "vendor": "지에프테크",
          "pricing": {
            "supply_price": null,
            "selling_price": null
          }
        },
        {
          "idx": "686",
          "product_name": "32파이 일반펌프",
          "product_code": "PO032-CG06(민)",
          "neck_size": "32파이",
          "category_type": "PUMP",
          "material": "기타",
          "spec": "32파이 일반펌프",
          "vendor": "지에프테크",
          "pricing": {
            "supply_price": null,
            "selling_price": null
          }
        },
        {
          "idx": "684",
          "product_name": "32파이 일반펌프",
          "product_code": "PO032-CG05(민)",
          "neck_size": "32파이",
          "category_type": "PUMP",
          "material": "기타",
          "spec": "32파이 일반펌프",
          "vendor": "지에프테크",
          "pricing": {
            "supply_price": null,
            "selling_price": null
          }
        }
      ]
    },
    "recommended_applications": {
      "by_capacity": [],
      "by_material": [
        "수분 기반 토너",
        "로션/에멀젼",
        "에센스 (저점도)",
        "민감성 제품",
        "베이비 케어"
      ],
      "combined_recommendation": [],
      "unsuitable_products": [
        "고농도 오일 (>30%)",
        "고농도 알코올 (>30%)",
        "강산성 제품 (pH <3)",
        "강염기성 제품 (pH >11)"
      ],
      "material_warnings": [],
      "chemical_resistance": {
        "water_based": "excellent",
        "low_oil": "good",
        "high_oil": "poor",
        "alcohol_low": "good",
        "alcohol_high": "avoid",
        "ph_range": "4-10"
      }
    },
    "material_info": {
      "name": "Polyethylene (폴리에틸렌)",
      "characteristics": "내화학성 우수, 유연성, 경제적",
      "suitable_products": [
        "수분 기반 토너",
        "로션/에멀젼",
        "에센스 (저점도)",
        "민감성 제품",
        "베이비 케어"
      ],
      "unsuitable_products": [
        "고농도 오일 (>30%)",
        "고농도 알코올 (>30%)",
        "강산성 제품 (pH <3)",
        "강염기성 제품 (pH >11)"
      ],
      "chemical_resistance": {
        "water_based": "excellent",
        "low_oil": "good",
        "high_oil": "poor",
        "alcohol_low": "good",
        "alcohol_high": "avoid",
        "ph_range": "4-10"
      }
    }
  }
}